arxiv_query_fluent/__init__.py
arxiv_query_fluent-0.0.1.dist-info/LICENSE
arxiv_query_fluent-0.0.1.dist-info/METADATA
arxiv_query_fluent-0.0.1.dist-info/WHEEL
arxiv_query_fluent-0.0.1.dist-info/top_level.txt
arxiv_query_fluent-0.0.1.dist-info/RECORD
