Metadata-Version: 2.2
Name: arxiv_query_fluent
Version: 0.0.1
Summary: A Python library providing a fluent, intuitive, and chainable interface for easily building complex arXiv API queries, simplifying data retrieval and integration into your workflow.
Author-email: Michael Lee <michael@ifugood.com>
License: MIT
Project-URL: Homepage, https://github.com/maikeruSan/arxiv_query_fluent
Project-URL: Repository, https://github.com/maikeruSan/arxiv_query_fluent
Classifier: Programming Language :: Python :: 3
Classifier: License :: OSI Approved :: MIT License
Classifier: Operating System :: OS Independent
Requires-Python: >=3.8
License-File: LICENSE
Requires-Dist: arxiv>=2.1.3
Requires-Dist: pytest>=8.3.5
